main.py
setup.py
v2xlm_gml.egg-info/PKG-INFO
v2xlm_gml.egg-info/SOURCES.txt
v2xlm_gml.egg-info/dependency_links.txt
v2xlm_gml.egg-info/requires.txt
v2xlm_gml.egg-info/top_level.txt